{
  "version": "1",
  "cognitoConfig": {
    "identityPoolName": "knowhizpool5f6ba34f_identitypool_5f6ba34f",
    "allowUnauthenticatedIdentities": false,
    "resourceNameTruncated": "knowhi5f6ba34f",
    "userPoolName": "knowhizpool5f6ba34f_userpool_5f6ba34f",
    "autoVerifiedAttributes": [
      "email"
    ],
    "mfaConfiguration": "OFF",
    "mfaTypes": [
      "SMS Text Message"
    ],
    "smsAuthenticationMessage": "Your authentication code is {####}",
    "smsVerificationMessage": "Your verification code is {####}",
    "emailVerificationSubject": "Your verification code",
    "emailVerificationMessage": "Your verification code is {####}",
    "defaultPasswordPolicy": false,
    "passwordPolicyMinLength": 8,
    "passwordPolicyCharacters": [],
    "requiredAttributes": [
      "email"
    ],
    "aliasAttributes": [],
    "userpoolClientGenerateSecret": false,
    "userpoolClientRefreshTokenValidity": 30,
    "userpoolClientWriteAttributes": [
      "email"
    ],
    "userpoolClientReadAttributes": [
      "email"
    ],
    "userpoolClientLambdaRole": "knowhi5f6ba34f_userpoolclient_lambda_role",
    "userpoolClientSetAttributes": false,
    "sharedId": "5f6ba34f",
    "resourceName": "knowhizpool5f6ba34f",
    "authSelections": "identityPoolAndUserPool",
    "useDefault": "defaultSocial",
    "hostedUI": true,
    "usernameAttributes": [
      "email"
    ],
    "hostedUIDomainName": "knowhizpool5f6ba34f-5f6ba34f",
    "authProvidersUserPool": [
      "Google",
      "SignInWithApple"
    ],
    "hostedUIProviderMeta": "[{\"ProviderName\":\"Google\",\"authorize_scopes\":\"openid email profile\",\"AttributeMapping\":{\"email\":\"email\",\"username\":\"sub\"}},{\"ProviderName\":\"SignInWithApple\",\"authorize_scopes\":\"email\",\"AttributeMapping\":{\"email\":\"email\"}}]",
    "userPoolGroupList": [],
    "serviceName": "Cognito",
    "usernameCaseSensitive": false,
    "useEnabledMfas": true,
    "authRoleArn": {
      "Fn::GetAtt": [
        "AuthRole",
        "Arn"
      ]
    },
    "unauthRoleArn": {
      "Fn::GetAtt": [
        "UnauthRole",
        "Arn"
      ]
    },
    "breakCircularDependency": true,
    "dependsOn": [],
    "oAuthMetadata": "{\"AllowedOAuthFlows\":[\"code\"],\"AllowedOAuthScopes\":[\"phone\",\"email\",\"openid\",\"profile\",\"aws.cognito.signin.user.admin\"],\"CallbackURLs\":[\"http://localhost:3000/\",\"https://www.knowhiz.us/\",\"myapp://\"],\"LogoutURLs\":[\"http://localhost:3000/\",\"https://www.knowhiz.us/\",\"myapp://\"]}"
  }
}